AUTHORS
Changelog.rst
MANIFEST.in
README.rst
setup.py
django_mongodb_engine/__init__.py
django_mongodb_engine/base.py
django_mongodb_engine/client.py
django_mongodb_engine/compiler.py
django_mongodb_engine/creation.py
django_mongodb_engine/fields.py
django_mongodb_engine/models.py
django_mongodb_engine/query.py
django_mongodb_engine/router.py
django_mongodb_engine/serializer.py
django_mongodb_engine/south.py
django_mongodb_engine/utils.py
django_mongodb_engine/widgets.py
django_mongodb_engine.egg-info/PKG-INFO
django_mongodb_engine.egg-info/SOURCES.txt
django_mongodb_engine.egg-info/dependency_links.txt
django_mongodb_engine.egg-info/requires.txt
django_mongodb_engine.egg-info/top_level.txt
django_mongodb_engine/contrib/__init__.py
django_mongodb_engine/contrib/aggregations.py
django_mongodb_engine/contrib/mapreduce.py