Metadata-Version: 1.0
Name: django-mongodb-engine
Version: 0.3.0
Summary: A MongoDB backend standing outside django.
Home-page: http://github.com/django-mongodb-engine/mongodb-engine
Author: Flavio Percoco Premoli, Alberto Paro, Jonas Haag and contributors
Author-email: django-non-relational@googlegroups.com
License: 2-clause BSD
Platform: any
Classifier: Intended Audience :: Developers
Classifier: License :: OSI Approved :: BSD License
Classifier: Programming Language :: Python
Classifier: Topic :: Internet
Classifier: Topic :: Database
Classifier: Topic :: Software Development :: Libraries :: Python Modules
Classifier: Operating System :: OS Independent
Classifier: Programming Language :: Python :: 2
Classifier: Programming Language :: Python :: 2.4
Classifier: Programming Language :: Python :: 2.5
Classifier: Programming Language :: Python :: 2.6
Classifier: Programming Language :: Python :: 2.7
